smart_config/__init__.py
smart_config/smart_config.py
smart_config-0.1.3.dist-info/LICENSE
smart_config-0.1.3.dist-info/METADATA
smart_config-0.1.3.dist-info/WHEEL
smart_config-0.1.3.dist-info/top_level.txt
smart_config-0.1.3.dist-info/RECORD
