Metadata-Version: 2.1
Name: smart-config
Version: 0.1.3
Summary: Simple configuration file loader
Home-page: https://github.com/sfahad1414/conf_loader
Author: Fahad Ali Shaikh
Author-email: shaikhfahad2526@gmail.com
License: MIT
Platform: any
Classifier: Operating System :: OS Independent
Classifier: License :: OSI Approved :: MIT License
Classifier: Topic :: Utilities
Classifier: Intended Audience :: Developers
Classifier: Topic :: Software Development :: Libraries :: Python Modules
Classifier: Programming Language :: Python :: 3.5
Classifier: Programming Language :: Python :: 3.6
Classifier: Programming Language :: Python :: 3.7
Classifier: Programming Language :: Python :: 3.8
Requires-Python: >=3.5
Requires-Dist: pyyaml
Requires-Dist: toml
Requires-Dist: loguru
